AUTHORS
LICENSE
MANIFEST.in
README
setup.cfg
setup.py
MergeImprove/MergeImprove.py
MergeImprove/Pileup.py
MergeImprove/__init__.py
MergeImprove/util.py
bin/pysuspenders
suspenders.egg-info/PKG-INFO
suspenders.egg-info/SOURCES.txt
suspenders.egg-info/dependency_links.txt
suspenders.egg-info/not-zip-safe
suspenders.egg-info/requires.txt
suspenders.egg-info/top_level.txt