Metadata-Version: 1.0
Name: suspenders
Version: 0.2.6
Summary: Allows the merging of alignments that have been annotated using pylapels into a single alignment that picks the highest quality alignment.
Home-page: http://code.google.com/p/suspenders
Author: James Holt
Author-email: holtjma@cs.unc.edu
License: MIT
Platform: UNKNOWN
